kalkan_crypt/__init__.py
kalkan_crypt/adapter.py
kalkan_crypt/enums.py
kalkan_crypt/exceptions.py
kalkan_crypt/dll/libkalkancryptwr-64.so.2.0.2
kalkan_crypt-0.1.0.dist-info/METADATA
kalkan_crypt-0.1.0.dist-info/WHEEL
kalkan_crypt-0.1.0.dist-info/top_level.txt
kalkan_crypt-0.1.0.dist-info/RECORD
